cript/__init__.py
cript/exceptions.py
cript/api/__init__.py
cript/api/api.py
cript/api/api_config.py
cript/api/data_schema.py
cript/api/exceptions.py
cript/api/paginator.py
cript/api/valid_search_modes.py
cript/api/vocabulary_categories.py
cript/api/utils/__init__.py
cript/api/utils/aws_s3_utils.py
cript/api/utils/get_host_token.py
cript/api/utils/helper_functions.py
cript/api/utils/save_helper.py
cript/api/utils/web_file_downloader.py
cript/nodes/__init__.py
cript/nodes/core.py
cript/nodes/exceptions.py
cript/nodes/node_iterator.py
cript/nodes/uuid_base.py
cript/nodes/primary_nodes/__init__.py
cript/nodes/primary_nodes/collection.py
cript/nodes/primary_nodes/computation.py
cript/nodes/primary_nodes/computation_process.py
cript/nodes/primary_nodes/data.py
cript/nodes/primary_nodes/experiment.py
cript/nodes/primary_nodes/inventory.py
cript/nodes/primary_nodes/material.py
cript/nodes/primary_nodes/primary_base_node.py
cript/nodes/primary_nodes/process.py
cript/nodes/primary_nodes/project.py
cript/nodes/primary_nodes/reference.py
cript/nodes/subobjects/__init__.py
cript/nodes/subobjects/algorithm.py
cript/nodes/subobjects/citation.py
cript/nodes/subobjects/computational_forcefield.py
cript/nodes/subobjects/condition.py
cript/nodes/subobjects/equipment.py
cript/nodes/subobjects/ingredient.py
cript/nodes/subobjects/parameter.py
cript/nodes/subobjects/property.py
cript/nodes/subobjects/quantity.py
cript/nodes/subobjects/software.py
cript/nodes/subobjects/software_configuration.py
cript/nodes/supporting_nodes/__init__.py
cript/nodes/supporting_nodes/file.py
cript/nodes/supporting_nodes/user.py
cript/nodes/util/__init__.py
cript/nodes/util/core.py
cript/nodes/util/json.py
cript-2.4.0.dist-info/LICENSE.md
cript-2.4.0.dist-info/METADATA
cript-2.4.0.dist-info/WHEEL
cript-2.4.0.dist-info/top_level.txt
cript-2.4.0.dist-info/RECORD
