Metadata-Version: 2.1
Name: cript
Version: 2.4.0
Summary: CRIPT Python SDK
Home-page: https://github.com/C-Accel-CRIPT/Python-SDK
Author: CRIPT Development Team
License: MIT
Platform: any
Classifier: Development Status :: 3 - Alpha
Classifier: Topic :: Scientific/Engineering
Classifier: Programming Language :: Python :: 3
Classifier: Programming Language :: Python :: 3 :: Only
Classifier: Programming Language :: Python :: 3.10
Requires-Python: >=3.10
License-File: LICENSE.md
Requires-Dist: requests ==2.31.0
Requires-Dist: jsonschema >=4.17.3
Requires-Dist: beartype ==0.14.1
Requires-Dist: boto3 ==1.28.39
